vidtoolz_replace_audio/__init__.py
vidtoolz_replace_audio-0.0.2.dist-info/licenses/LICENSE
vidtoolz_replace_audio-0.0.2.dist-info/METADATA
vidtoolz_replace_audio-0.0.2.dist-info/WHEEL
vidtoolz_replace_audio-0.0.2.dist-info/entry_points.txt
vidtoolz_replace_audio-0.0.2.dist-info/top_level.txt
vidtoolz_replace_audio-0.0.2.dist-info/RECORD
