Metadata-Version: 2.4
Name: vidtoolz-replace-audio
Version: 0.0.2
Summary: Replace audio for a video file
Author: Sukhbinder Singh
License: Apache-2.0
Project-URL: Homepage, https://github.com/sukhbinder/vidtoolz-replace-audio
Project-URL: Changelog, https://github.com/sukhbinder/vidtoolz-replace-audio/releases
Project-URL: Issues, https://github.com/sukhbinder/vidtoolz-replace-audio/issues
Project-URL: CI, https://github.com/sukhbinder/vidtoolz-replace-audio/actions
Classifier: License :: OSI Approved :: Apache Software License
License-File: LICENSE
Requires-Dist: vidtoolz
Provides-Extra: test
Requires-Dist: pytest; extra == "test"
Dynamic: license-file
